setup.py
blake256/blake256.py
blake256/test.py
blake256.egg-info/PKG-INFO
blake256.egg-info/SOURCES.txt
blake256.egg-info/dependency_links.txt
blake256.egg-info/top_level.txt