Metadata-Version: 1.1
Name: blake256
Version: 0.1.1
Summary: A Python module supporting blake256 hashing
Home-page: https://github.com/cipherzzz/blake256_hash
Author: cipherZ
Author-email: UNKNOWN
License: MIT
Download-URL: https://github.com/cipherzzz/blake256_hash/tarball/0.1.1
Platform: UNKNOWN
